forge/__init__.py
forge/core/__init__.py
forge/core/engine/__init__.py
forge/core/engine/color.py
forge/core/engine/constants.py
forge/core/engine/display.py
forge/core/engine/game.py
forge/core/engine/image.py
forge/core/engine/renderer.py
forge/core/engine/settings.py
forge/core/engine/sprite.py
forge/core/engine/timer.py
forge/core/managers/__init__.py
forge/core/managers/event.py
forge/core/managers/keyboard.py
forge/core/managers/mouse.py
forge/core/physics/__init__.py
forge/core/physics/vector.py
forge/core/physics/world.py
forge/core/utils/__init__.py
forge/core/utils/aliases.py
forge/core/utils/base.py
forge/core/utils/dispatch.py
forge/core/utils/exceptions.py
forge/core/utils/id.py
forge/core/utils/loaders.py
forge/core/utils/math.py
forge/hearth/__init__.py
forge/hearth/settings.py
forge/hearth/components/__init__.py
forge/hearth/components/base.py
forge/hearth/components/button.py
forge/hearth/components/checkbox.py
forge/hearth/components/slider.py
forge/hearth/elements/__init__.py
forge/hearth/elements/base.py
forge/hearth/elements/debug.py
forge/hearth/elements/shapes.py
forge/hearth/elements/text.py
forge/hearth/utils/__init__.py
forge/hearth/utils/bounds.py
game_forge-0.4.0.dist-info/METADATA
game_forge-0.4.0.dist-info/WHEEL
game_forge-0.4.0.dist-info/licenses/LICENSE
game_forge-0.4.0.dist-info/RECORD
