Metadata-Version: 2.1
Name: game-forge
Version: 0.4.0
Summary: A Pygame wrapper for making simple, yet detailed 2D games and experiences.
Project-URL: Homepage, https://github.com/k-srivastava/Forge/
Project-URL: Bug Tracker, https://github.com/k-srivastava/Forge/issues
Author-email: Kshitij Srivastava <kshitijsrivastava2312@gmail.com>
License:                   GNU LESSER GENERAL PUBLIC LICENSE
License-File: LICENSE
Classifier: License :: OSI Approved :: GNU General Public License v2 or later (GPLv2+)
Classifier: Operating System :: OS Independent
Classifier: Programming Language :: Python :: 3
Requires-Python: >=3.11
